setup.py
muSys.egg-info/PKG-INFO
muSys.egg-info/SOURCES.txt
muSys.egg-info/dependency_links.txt
muSys.egg-info/requires.txt
muSys.egg-info/top_level.txt
musys/__init__.py
musys/deltamem/__init__.py
musys/deltamem/memchan.py
musys/deltamem/netmem.py
musys/taumem/__init__.py
musys/taumem/taumem.py