Metadata-Version: 1.1
Name: muSys
Version: 0.1.1
Summary: A simple network attatched memory module
Home-page: UNKNOWN
Author: Josh Bosley
Author-email: bosley117@gmail.com
License: MIT
Platform: UNKNOWN
Classifier: Programming Language :: Python
Classifier: License :: OSI Approved :: MIT License
Classifier: Intended Audience :: Developers
Classifier: Topic :: Database
